fastanp/AUTH_UPDATE_SUMMARY.md
fastanp/CONTEXT_UPDATES.md
fastanp/DESIGN.md
fastanp/IMPLEMENTATION.md
fastanp/METRICS_AFTER.json
fastanp/METRICS_BEFORE.json
fastanp/QUICKSTART.md
fastanp/README.md
fastanp/TEST_REPORT.md
fastanp/__init__.py
fastanp/ad/__init__.py
fastanp/ad/generator.py
fastanp/ad/information.py
fastanp/app/__init__.py
fastanp/app/plugin.py
fastanp/auth/__init__.py
fastanp/auth/middleware.py
fastanp/context/__init__.py
fastanp/context/context.py
fastanp/context/session.py
fastanp/context/session_manager.py
fastanp/interfaces/__init__.py
fastanp/interfaces/jsonrpc.py
fastanp/interfaces/manager.py
fastanp/interfaces/openrpc.py
fastanp/interfaces/proxy.py
fastanp/interfaces/registered_function.py
fastanp/interfaces/utils.py
fastanp/models/__init__.py
fastanp/utils/__init__.py
fastanp-0.1.1.dist-info/METADATA
fastanp-0.1.1.dist-info/WHEEL
fastanp-0.1.1.dist-info/licenses/LICENSE
fastanp-0.1.1.dist-info/RECORD
