Metadata-Version: 2.4
Name: fastanp
Version: 0.1.1
Summary: Build ANP protocol services quickly
Project-URL: Homepage, https://github.com/whillhill/fastanp
Project-URL: Repository, https://github.com/whillhill/fastanp
Author-email: whillhill <ooooofish@126.com>
License: MIT License
License-File: LICENSE
Keywords: ANP,FastAPI,agent,protocol
Classifier: License :: OSI Approved :: MIT License
Classifier: Operating System :: OS Independent
Classifier: Programming Language :: Python :: 3
Requires-Python: >=3.10
Requires-Dist: anp>=0.4.7
Requires-Dist: fastapi>=0.115.4
Requires-Dist: pydantic<3.0.0,>=2.9.2
